synthra/__init__.py
synthra/logger.py
synthra-0.1.2.dist-info/licenses/LICENSE
synthra-0.1.2.dist-info/METADATA
synthra-0.1.2.dist-info/WHEEL
synthra-0.1.2.dist-info/top_level.txt
synthra-0.1.2.dist-info/RECORD
